MANIFEST.in
README.md
requirements.txt
requirements_dev.txt
setup.py
pylint_args/__init__.py
pylint_args/messages.py
pylint_args.egg-info/PKG-INFO
pylint_args.egg-info/SOURCES.txt
pylint_args.egg-info/dependency_links.txt
pylint_args.egg-info/requires.txt
pylint_args.egg-info/top_level.txt
pylint_args/checkers/__init__.py
pylint_args/checkers/alphabeticalkwargsorderchecker.py
pylint_args/checkers/argsnamechecker.py
pylint_args/checkers/base.py
pylint_args/checkers/kwargsnamechecker.py
pylint_args/checkers/kwargsorderchecker.py
tests/__init__.py
tests/test_argsnamechecker.py
tests/test_kwargsnamechecker.py
tests/test_kwargsorderchecker.py